LICENSE
MANIFEST.in
README.rst
setup.cfg
setup.py
versioneer.py
pychimera/__init__.py
pychimera/__main__.py
pychimera/_version.py
pychimera/core.py
pychimera/jupyter_utils.py
pychimera.egg-info/PKG-INFO
pychimera.egg-info/SOURCES.txt
pychimera.egg-info/dependency_links.txt
pychimera.egg-info/top_level.txt
pychimera/data/__init__.py
pychimera/data/logo.png
pychimera/platforms/__init__.py
pychimera/platforms/linux.py
pychimera/platforms/osx.py
pychimera/platforms/win.py
scripts/pychimera