Metadata-Version: 1.1
Name: pychimera
Version: 0.2.6
Summary: Use UCSF Chimera Python API in a standard Python 2.7 interpreter.
Home-page: https://github.com/insilichem/pychimera
Author: Jaime Rodríguez-Guerra
Author-email: jaime.rogue@gmail.com
License: LGPL
Download-URL: https://github.com/insilichem/pychimera/tarball/v0.2.6
Platform: any
Classifier: Programming Language :: Python :: 2.7
Classifier: Development Status :: 3 - Alpha
Classifier: Natural Language :: English
Classifier: Environment :: Console
Classifier: Intended Audience :: Science/Research
Classifier: License :: OSI Approved :: GNU Library or Lesser General Public License (LGPL)
Classifier: Operating System :: OS Independent
Classifier: Topic :: Scientific/Engineering :: Chemistry
